{"_id":{"$oid":"596ffb07dfdbad1f20f4f7b9"},"name":"Pan","default":127,"catagory":"Position","__v":0}
{"_id":{"$oid":"596ffb0cdfdbad1f20f4f7ba"},"name":"Tilt","default":127,"catagory":"Position","__v":0}
{"_id":{"$oid":"596ffb20dfdbad1f20f4f7bb"},"name":"Red","default":0,"catagory":"Color","__v":0}
{"_id":{"$oid":"596ffb24dfdbad1f20f4f7bc"},"name":"Green","default":0,"catagory":"Color","__v":0}
{"_id":{"$oid":"596ffb28dfdbad1f20f4f7bd"},"name":"Blue","default":0,"catagory":"Color","__v":0}
{"_id":{"$oid":"596ffb2ddfdbad1f20f4f7be"},"name":"Amber","default":0,"catagory":"Color","__v":0}
{"_id":{"$oid":"596ffb33dfdbad1f20f4f7bf"},"name":"White","default":0,"catagory":"Color","__v":0}
{"_id":{"$oid":"596ffb37dfdbad1f20f4f7c0"},"name":"UV","default":0,"catagory":"Color","__v":0}
{"_id":{"$oid":"596ffb5adfdbad1f20f4f7c1"},"name":"Zoom","default":127,"catagory":"Focus","__v":0}
{"_id":{"$oid":"596ffb60dfdbad1f20f4f7c2"},"name":"Focus","default":127,"catagory":"Focus","__v":0}
{"_id":{"$oid":"596ffb69dfdbad1f20f4f7c3"},"name":"Shutter","default":127,"catagory":"Beam","__v":0}
{"_id":{"$oid":"596ffb83dfdbad1f20f4f7c4"},"name":"Effect","default":0,"catagory":"Beam","__v":0}
{"_id":{"$oid":"596ffb8fdfdbad1f20f4f7c5"},"name":"Dimmer","default":0,"catagory":"Dimmer","__v":0}
{"_id":{"$oid":"596ffba1dfdbad1f20f4f7c6"},"name":"Reset","default":0,"catagory":"Control","__v":0}
{"_id":{"$oid":"596ffbaadfdbad1f20f4f7c7"},"name":"Speed1","default":0,"catagory":"Control","__v":0}
{"_id":{"$oid":"596ffbb0dfdbad1f20f4f7c8"},"name":"Speed2","default":0,"catagory":"Control","__v":0}
{"_id":{"$oid":"596ffbb6dfdbad1f20f4f7c9"},"name":"Macro","default":0,"catagory":"Control","__v":0}
{"_id":{"$oid":"596ffbdadfdbad1f20f4f7ca"},"name":"Gobo","default":0,"catagory":"Gobo","__v":0}
{"_id":{"$oid":"596ffbdddfdbad1f20f4f7cb"},"name":"Gobo2","default":0,"catagory":"Gobo","__v":0}
